querysutra-0.5.3.dist-info/licenses/LICENSE
sutra/__init__.py
sutra/cache_manager.py
sutra/clear_cache.py
sutra/core.py
sutra/data_loader.py
sutra/database_manager.py
sutra/direct_query.py
sutra/feedback.py
sutra/feedback_matcher.py
sutra/nlp_processor.py
sutra/schema_embeddings.py
sutra/schema_generator.py
sutra/sutra.py
sutra/sutra_client.py
sutra/sutra_core.py
sutra/sutra_simple.py
sutra/visualizer.py
tests/__init__.py
tests/test_modules.py
tests/test_sutra.py
utils/__init__.py
utils/file_utils.py
utils/text_utils.py
querysutra-0.5.3.dist-info/METADATA
querysutra-0.5.3.dist-info/WHEEL
querysutra-0.5.3.dist-info/top_level.txt
querysutra-0.5.3.dist-info/RECORD
