Metadata-Version: 2.4
Name: QuerySUTRA
Version: 0.5.3
Summary: SUTRA
Author: Aditya Batta
License: MIT
Requires-Python: >=3.8
License-File: LICENSE
Requires-Dist: pandas>=1.3.0
Requires-Dist: numpy>=1.21.0
Requires-Dist: openai>=1.0.0
Requires-Dist: plotly>=5.0.0
Requires-Dist: matplotlib>=3.3.0
Requires-Dist: PyPDF2>=3.0.0
Requires-Dist: python-docx>=0.8.11
Requires-Dist: openpyxl>=3.0.0
Provides-Extra: mysql
Requires-Dist: sqlalchemy>=1.4.0; extra == "mysql"
Requires-Dist: mysql-connector-python>=8.0.0; extra == "mysql"
Provides-Extra: postgres
Requires-Dist: sqlalchemy>=1.4.0; extra == "postgres"
Requires-Dist: psycopg2-binary>=2.9.0; extra == "postgres"
Provides-Extra: embeddings
Requires-Dist: sentence-transformers>=2.0.0; extra == "embeddings"
Provides-Extra: all
Requires-Dist: sqlalchemy>=1.4.0; extra == "all"
Requires-Dist: mysql-connector-python>=8.0.0; extra == "all"
Requires-Dist: psycopg2-binary>=2.9.0; extra == "all"
Requires-Dist: sentence-transformers>=2.0.0; extra == "all"
Dynamic: license-file
Dynamic: requires-python
